tiny_ai_client/__init__.py
tiny_ai_client/anthropic_.py
tiny_ai_client/gemini_.py
tiny_ai_client/groq_.py
tiny_ai_client/models.py
tiny_ai_client/ollama_.py
tiny_ai_client/openai_.py
tiny_ai_client/tools.py
tiny_ai_client/vision.py
tiny_ai_client-0.0.14.dist-info/LICENSE
tiny_ai_client-0.0.14.dist-info/METADATA
tiny_ai_client-0.0.14.dist-info/WHEEL
tiny_ai_client-0.0.14.dist-info/RECORD
