Metadata-Version: 2.1
Name: tiny-ai-client
Version: 0.0.14
Summary: Tiny AI client for LLMs. As simple as it gets.
License: Apache 2.0
Author: piEsposito
Author-email: piero.skywalker@gmail.com
Requires-Python: >=3.9
Classifier: License :: Other/Proprietary License
Classifier: Programming Language :: Python :: 3
Classifier: Programming Language :: Python :: 3.9
Classifier: Programming Language :: Python :: 3.10
Classifier: Programming Language :: Python :: 3.11
Classifier: Programming Language :: Python :: 3.12
Classifier: Programming Language :: Python :: 3.13
Requires-Dist: aiohttp (>=3.10.3,<4.0.0)
Requires-Dist: anthropic (==0.42.0)
Requires-Dist: groq (==0.13.1)
Requires-Dist: openai (==1.58.1)
Requires-Dist: pillow (==11)
Requires-Dist: pydantic (==2.7.3)
Requires-Dist: python-dotenv (>=1.0.1,<2.0.0)
